{
  "forge_marker": 1,
  "defaults": {
	"model": "solar:prism_flower_0"
  },
  "variants": {
	"normal": [{
	}],
    "inventory": [{
		"model": "solar:item/prism_flower"
	}],
	"facing": {
	  "down" : {
	  },
	  "up": {
		"model": "solar:prism_flower_2"
	  },
	  "north": {
		"model": "solar:prism_flower_1"
	  },
	  "south": {
		"model": "solar:prism_flower_1",
		"y": 180
	  },
	  "west": {
		"model": "solar:prism_flower_1",
		"y": 270
	  },
	  "east": {
		"model": "solar:prism_flower_1",
		"y": 90
	  }
	}
  }
}